orca_studio/__init__.py
orca_studio/molecule.py
orca_studio/orca_output.py
orca_studio/periodic_table.json
orca_studio/apps/__init__.py
orca_studio/apps/plots.py
orca_studio/apps/tddft.py
orca_studio/cli/__init__.py
orca_studio/cli/scan_mode.py
orca_studio/parse/__init__.py
orca_studio/parse/ailft.py
orca_studio/parse/common.py
orca_studio/parse/xyz.py
orca_studio/parse/ir/__init__.py
orca_studio/parse/ir/hessian.py
orca_studio/parse/ir/ir_spectrum.py
orca_studio/parse/ir/normal_modes.py
orca_studio/parse/ir/vibrational_frequencies.py
orca_studio/parse/metadata/__init__.py
orca_studio/parse/metadata/metadata.py
orca_studio/parse/tddft/__init__.py
orca_studio/parse/tddft/absorption_spectra.py
orca_studio/parse/tddft/tda.py
orca_studio/parse/thermodynamics/__init__.py
orca_studio/parse/thermodynamics/enthalpy.py
orca_studio/parse/thermodynamics/entropy_correction.py
orca_studio/parse/thermodynamics/fspe.py
orca_studio/parse/thermodynamics/gibbs_correction.py
orca_studio/parse/thermodynamics/gibbs_free_energy.py
orca_studio/parse/thermodynamics/thermal_correction.py
orca_studio/parse/thermodynamics/zero_point_energy.py
orca_studio/render/__init__.py
orca_studio/render/create_densities.py
orca_studio/render/isosurface_renderer.py
orca_studio/render/meshes.py
orca_studio/render/molecular_render.py
orca_studio/render/renderer.py
orca_studio-0.2.17.dist-info/METADATA
orca_studio-0.2.17.dist-info/WHEEL
orca_studio-0.2.17.dist-info/entry_points.txt
orca_studio-0.2.17.dist-info/licenses/LICENSE
orca_studio-0.2.17.dist-info/RECORD
