Metadata-Version: 2.4
Name: orca-studio
Version: 0.2.17
Summary: A Python toolkit for parsing, analyzing, and visualizing ORCA quantum chemistry calculations
License-Expression: MIT
License-File: LICENSE
Requires-Python: >=3.11
Requires-Dist: click>=8.2.1
Requires-Dist: marimo>=0.13.14
Requires-Dist: numpy>=2.2.6
Requires-Dist: plotly>=6.1.2
Requires-Dist: polars>=1.30.0
Requires-Dist: rdkit>=2025.3.2
Requires-Dist: ruff>=0.12.1
Requires-Dist: scikit-image>=0.25.2
Requires-Dist: scipy>=1.15.3
